awslabs/__init__.py
awslabs/core_mcp_server/__init__.py
awslabs/core_mcp_server/server.py
awslabs/core_mcp_server/static/PROMPT_UNDERSTANDING.md
awslabs/core_mcp_server/static/__init__.py
dungngo_awslabs_core_mcp_server-1.0.9.dist-info/METADATA
dungngo_awslabs_core_mcp_server-1.0.9.dist-info/WHEEL
dungngo_awslabs_core_mcp_server-1.0.9.dist-info/entry_points.txt
dungngo_awslabs_core_mcp_server-1.0.9.dist-info/licenses/LICENSE
dungngo_awslabs_core_mcp_server-1.0.9.dist-info/licenses/NOTICE
dungngo_awslabs_core_mcp_server-1.0.9.dist-info/RECORD
