Metadata-Version: 2.4
Name: dungngo-awslabs.core-mcp-server
Version: 1.0.9
Summary: An AWS Labs Model Context Protocol (MCP) server for aswlabs Core MCP Server (republished for testing)
Project-URL: Homepage, https://awslabs.github.io/mcp/
Project-URL: Documentation, https://awslabs.github.io/mcp/servers/core-mcp-server/
Project-URL: Source, https://github.com/awslabs/mcp.git
Project-URL: Bug Tracker, https://github.com/awslabs/mcp/issues
Project-URL: Changelog, https://github.com/awslabs/mcp/blob/main/src/core-mcp-server/CHANGELOG.md
Author-email: dungngo <test@dungngo.dev>
License: Apache-2.0
License-File: LICENSE
License-File: NOTICE
Classifier: License :: OSI Approved :: Apache Software License
Classifier: Operating System :: OS Independent
Classifier: Programming Language :: Python
Classifier: Programming Language :: Python :: 3
Classifier: Programming Language :: Python :: 3.10
Classifier: Programming Language :: Python :: 3.11
Classifier: Programming Language :: Python :: 3.12
Classifier: Programming Language :: Python :: 3.13
Requires-Python: >=3.10
Requires-Dist: awslabs-amazon-kendra-index-mcp-server>=1.0.3
Requires-Dist: awslabs-amazon-keyspaces-mcp-server>=0.0.3
Requires-Dist: awslabs-amazon-mq-mcp-server>=2.0.4
Requires-Dist: awslabs-amazon-neptune-mcp-server>=1.0.2
Requires-Dist: awslabs-amazon-sns-sqs-mcp-server>=2.0.4
Requires-Dist: awslabs-aurora-dsql-mcp-server>=1.0.3
Requires-Dist: awslabs-aws-api-mcp-server>=0.2.2
Requires-Dist: awslabs-aws-dataprocessing-mcp-server>=0.1.7
Requires-Dist: awslabs-aws-diagram-mcp-server>=1.0.5
Requires-Dist: awslabs-aws-documentation-mcp-server>=1.1.2
Requires-Dist: awslabs-aws-healthomics-mcp-server>=0.0.3
Requires-Dist: awslabs-aws-msk-mcp-server>=0.0.3
Requires-Dist: awslabs-aws-pricing-mcp-server>=1.0.8
Requires-Dist: awslabs-aws-serverless-mcp-server>=0.1.7
Requires-Dist: awslabs-aws-support-mcp-server>=0.1.7
Requires-Dist: awslabs-billing-cost-management-mcp-server>=0.0.2
Requires-Dist: awslabs-cdk-mcp-server>=1.0.4
Requires-Dist: awslabs-cfn-mcp-server>=1.0.6
Requires-Dist: awslabs-cloudtrail-mcp-server>=0.0.1
Requires-Dist: awslabs-cloudwatch-appsignals-mcp-server>=0.1.4
Requires-Dist: awslabs-cloudwatch-logs-mcp-server>=0.0.4
Requires-Dist: awslabs-cloudwatch-mcp-server>=0.0.7
Requires-Dist: awslabs-code-doc-gen-mcp-server>=1.0.2
Requires-Dist: awslabs-cost-analysis-mcp-server>=1.0.5
Requires-Dist: awslabs-cost-explorer-mcp-server>=0.0.8
Requires-Dist: awslabs-documentdb-mcp-server>=1.0.2
Requires-Dist: awslabs-dynamodb-mcp-server>=1.0.4
Requires-Dist: awslabs-ecs-mcp-server>=0.1.5
Requires-Dist: awslabs-eks-mcp-server>=0.1.8
Requires-Dist: awslabs-elasticache-mcp-server>=0.1.4
Requires-Dist: awslabs-finch-mcp-server>=0.1.4
Requires-Dist: awslabs-frontend-mcp-server>=1.0.3
Requires-Dist: awslabs-git-repo-research-mcp-server>=1.0.5
Requires-Dist: awslabs-iam-mcp-server>=1.0.3
Requires-Dist: awslabs-lambda-mcp-server>=1.0.0
Requires-Dist: awslabs-lambda-tool-mcp-server>=2.0.4
Requires-Dist: awslabs-memcached-mcp-server>=1.0.4
Requires-Dist: awslabs-mysql-mcp-server>=1.0.2
Requires-Dist: awslabs-nova-canvas-mcp-server>=1.0.3
Requires-Dist: awslabs-postgres-mcp-server>=1.0.4
Requires-Dist: awslabs-prometheus-mcp-server>=0.2.2
Requires-Dist: awslabs-redshift-mcp-server>=0.0.3
Requires-Dist: awslabs-s3-tables-mcp-server>=0.0.6
Requires-Dist: awslabs-stepfunctions-tool-mcp-server>=0.1.9
Requires-Dist: awslabs-syntheticdata-mcp-server>=1.0.3
Requires-Dist: awslabs-timestream-for-influxdb-mcp-server>=0.0.2
Requires-Dist: awslabs-well-architected-security-mcp-server>=0.1.1
Requires-Dist: boto3>=1.37.0
Requires-Dist: fastmcp>=2.11.1
Requires-Dist: loguru>=0.7.3
Requires-Dist: mcp[cli]>=1.11.0
Requires-Dist: pydantic>=2.10.6
Requires-Dist: python-dotenv>=1.0.1
